{
"meta":{"test_sets":[],"test_metrics":[],"learn_metrics":[{"best_value":"Min","name":"RMSE"}],"launch_mode":"Train","parameters":"","iteration_count":100,"learn_sets":["learn"],"name":"experiment"},
"iterations":[
{"learn":[39.31766747],"iteration":0,"passed_time":0.001774190016,"remaining_time":0.1756448115},
{"learn":[36.23820209],"iteration":1,"passed_time":0.003576470004,"remaining_time":0.1752470302},
{"learn":[33.12633418],"iteration":2,"passed_time":0.004885907461,"remaining_time":0.1579776746},
{"learn":[30.4598466],"iteration":3,"passed_time":0.006068233181,"remaining_time":0.1456375963},
{"learn":[27.84303839],"iteration":4,"passed_time":0.007277206229,"remaining_time":0.1382669184},
{"learn":[25.6400469],"iteration":5,"passed_time":0.008373221359,"remaining_time":0.131180468},
{"learn":[23.54948453],"iteration":6,"passed_time":0.009469704353,"remaining_time":0.1258117864},
{"learn":[21.61938785],"iteration":7,"passed_time":0.01042846151,"remaining_time":0.1199273074},
{"learn":[19.90281894],"iteration":8,"passed_time":0.01134374267,"remaining_time":0.1146978426},
{"learn":[18.25447147],"iteration":9,"passed_time":0.01225918436,"remaining_time":0.1103326593},
{"learn":[16.81036835],"iteration":10,"passed_time":0.01314699816,"remaining_time":0.1063711669},
{"learn":[15.470526],"iteration":11,"passed_time":0.01409175336,"remaining_time":0.1033395246},
{"learn":[14.26298925],"iteration":12,"passed_time":0.01500033978,"remaining_time":0.1003868893},
{"learn":[13.17291251],"iteration":13,"passed_time":0.01588720845,"remaining_time":0.09759285191},
{"learn":[12.30614693],"iteration":14,"passed_time":0.01699699486,"remaining_time":0.09631630422},
{"learn":[11.35099094],"iteration":15,"passed_time":0.01794365117,"remaining_time":0.09420416864},
{"learn":[10.55277241],"iteration":16,"passed_time":0.01905598517,"remaining_time":0.09303804523},
{"learn":[9.822276613],"iteration":17,"passed_time":0.02009710174,"remaining_time":0.09155346347},
{"learn":[9.111516516],"iteration":18,"passed_time":0.02105781858,"remaining_time":0.08977280552},
{"learn":[8.503827479],"iteration":19,"passed_time":0.0220440995,"remaining_time":0.088176398},
{"learn":[7.922470529],"iteration":20,"passed_time":0.0229441906,"remaining_time":0.08631385986},
{"learn":[7.389426457],"iteration":21,"passed_time":0.02384191416,"remaining_time":0.08453042294},
{"learn":[6.907562568],"iteration":22,"passed_time":0.02476069671,"remaining_time":0.08289450639},
{"learn":[6.446466114],"iteration":23,"passed_time":0.02567765553,"remaining_time":0.08131257585},
{"learn":[6.04278414],"iteration":24,"passed_time":0.02657674581,"remaining_time":0.07973023744},
{"learn":[5.658430957],"iteration":25,"passed_time":0.02746478957,"remaining_time":0.07816901646},
{"learn":[5.347328087],"iteration":26,"passed_time":0.02835864295,"remaining_time":0.07667336797},
{"learn":[5.03386039],"iteration":27,"passed_time":0.02922088688,"remaining_time":0.0751394234},
{"learn":[4.752891355],"iteration":28,"passed_time":0.03014010475,"remaining_time":0.07379129095},
{"learn":[4.474430293],"iteration":29,"passed_time":0.03104351501,"remaining_time":0.07243486837},
{"learn":[4.24290503],"iteration":30,"passed_time":0.03215256022,"remaining_time":0.07156537597},
{"learn":[4.034454493],"iteration":31,"passed_time":0.03330497223,"remaining_time":0.07077306599},
{"learn":[3.854317205],"iteration":32,"passed_time":0.03436884931,"remaining_time":0.0697791789},
{"learn":[3.672664005],"iteration":33,"passed_time":0.03524479366,"remaining_time":0.06841636416},
{"learn":[3.507539205],"iteration":34,"passed_time":0.03620093887,"remaining_time":0.06723031505},
{"learn":[3.36372122],"iteration":35,"passed_time":0.03711510786,"remaining_time":0.06598241396},
{"learn":[3.234541359],"iteration":36,"passed_time":0.03803100223,"remaining_time":0.06475549028},
{"learn":[3.120685504],"iteration":37,"passed_time":0.03897014666,"remaining_time":0.06358287087},
{"learn":[3.017706533],"iteration":38,"passed_time":0.03985178493,"remaining_time":0.062332279},
{"learn":[2.924694256],"iteration":39,"passed_time":0.04080209883,"remaining_time":0.06120314825},
{"learn":[2.834429843],"iteration":40,"passed_time":0.04174292527,"remaining_time":0.06006908758},
{"learn":[2.751551929],"iteration":41,"passed_time":0.04271919808,"remaining_time":0.05899317829},
{"learn":[2.700695317],"iteration":42,"passed_time":0.04370224227,"remaining_time":0.05793087929},
{"learn":[2.679721699],"iteration":43,"passed_time":0.04409614403,"remaining_time":0.05612236513},
{"learn":[2.656927994],"iteration":44,"passed_time":0.04505929637,"remaining_time":0.05507247334},
{"learn":[2.637334991],"iteration":45,"passed_time":0.04553543533,"remaining_time":0.05345464147},
{"learn":[2.592181223],"iteration":46,"passed_time":0.04666264627,"remaining_time":0.05261957984},
{"learn":[2.551474607],"iteration":47,"passed_time":0.04776520283,"remaining_time":0.0517456364},
{"learn":[2.532591334],"iteration":48,"passed_time":0.04874929701,"remaining_time":0.05073906424},
{"learn":[2.503138263],"iteration":49,"passed_time":0.04976121216,"remaining_time":0.04976121216},
{"learn":[2.48838512],"iteration":50,"passed_time":0.05018960431,"remaining_time":0.04822138453},
{"learn":[2.472442715],"iteration":51,"passed_time":0.05089740076,"remaining_time":0.04698221608},
{"learn":[2.422797888],"iteration":52,"passed_time":0.05195853645,"remaining_time":0.04607643798},
{"learn":[2.380627171],"iteration":53,"passed_time":0.05289925586,"remaining_time":0.04506232907},
{"learn":[2.346093653],"iteration":54,"passed_time":0.0538122071,"remaining_time":0.04402816944},
{"learn":[2.307347579],"iteration":55,"passed_time":0.05469976491,"remaining_time":0.04297838671},
{"learn":[2.28477957],"iteration":56,"passed_time":0.05564268987,"remaining_time":0.04197606428},
{"learn":[2.274754033],"iteration":57,"passed_time":0.05604637557,"remaining_time":0.04058530645},
{"learn":[2.262400834],"iteration":58,"passed_time":0.05654706044,"remaining_time":0.03929541488},
{"learn":[2.251231849],"iteration":59,"passed_time":0.05728025031,"remaining_time":0.03818683354},
{"learn":[2.21003949],"iteration":60,"passed_time":0.05823526744,"remaining_time":0.0372323841},
{"learn":[2.199530039],"iteration":61,"passed_time":0.05890887577,"remaining_time":0.03610543999},
{"learn":[2.17846903],"iteration":62,"passed_time":0.06003451318,"remaining_time":0.03525836488},
{"learn":[2.165759577],"iteration":63,"passed_time":0.06074881273,"remaining_time":0.03417120716},
{"learn":[2.140614502],"iteration":64,"passed_time":0.06191855889,"remaining_time":0.03334076248},
{"learn":[2.132240022],"iteration":65,"passed_time":0.0624659348,"remaining_time":0.03217942096},
{"learn":[2.11610281],"iteration":66,"passed_time":0.06317913158,"remaining_time":0.03111807973},
{"learn":[2.095369417],"iteration":67,"passed_time":0.06411482235,"remaining_time":0.03017168111},
{"learn":[2.089675921],"iteration":68,"passed_time":0.06439203845,"remaining_time":0.02892975641},
{"learn":[2.064549377],"iteration":69,"passed_time":0.0653546405,"remaining_time":0.02800913164},
{"learn":[2.05758022],"iteration":70,"passed_time":0.06602316811,"remaining_time":0.02696720951},
{"learn":[2.051593911],"iteration":71,"passed_time":0.06651093065,"remaining_time":0.02586536192},
{"learn":[2.024695608],"iteration":72,"passed_time":0.06740416937,"remaining_time":0.02493030922},
{"learn":[2.018779985],"iteration":73,"passed_time":0.06843921093,"remaining_time":0.02404620925},
{"learn":[1.989063634],"iteration":74,"passed_time":0.06937821363,"remaining_time":0.02312607121},
{"learn":[1.984014662],"iteration":75,"passed_time":0.06976185852,"remaining_time":0.02203006058},
{"learn":[1.978676329],"iteration":76,"passed_time":0.07030185272,"remaining_time":0.02099925471},
{"learn":[1.966990186],"iteration":77,"passed_time":0.07121387835,"remaining_time":0.02008596569},
{"learn":[1.942898743],"iteration":78,"passed_time":0.07211919044,"remaining_time":0.01917092404},
{"learn":[1.929205575],"iteration":79,"passed_time":0.07304942086,"remaining_time":0.01826235521},
{"learn":[1.923366825],"iteration":80,"passed_time":0.07399943104,"remaining_time":0.01735789123},
{"learn":[1.918686844],"iteration":81,"passed_time":0.07492024125,"remaining_time":0.01644590661},
{"learn":[1.914435222],"iteration":82,"passed_time":0.07598087075,"remaining_time":0.01556234702},
{"learn":[1.887404343],"iteration":83,"passed_time":0.07698215878,"remaining_time":0.01466326834},
{"learn":[1.883376887],"iteration":84,"passed_time":0.0777440757,"remaining_time":0.01371954277},
{"learn":[1.864078967],"iteration":85,"passed_time":0.0786509107,"remaining_time":0.01280363663},
{"learn":[1.860529235],"iteration":86,"passed_time":0.0795837856,"remaining_time":0.01189183003},
{"learn":[1.857680555],"iteration":87,"passed_time":0.07996695612,"remaining_time":0.01090458493},
{"learn":[1.854968483],"iteration":88,"passed_time":0.08035042456,"remaining_time":0.00993095135},
{"learn":[1.832332726],"iteration":89,"passed_time":0.0812530683,"remaining_time":0.0090281187},
{"learn":[1.829774892],"iteration":90,"passed_time":0.08160475664,"remaining_time":0.008070800107},
{"learn":[1.82728131],"iteration":91,"passed_time":0.08208859404,"remaining_time":0.007138138612},
{"learn":[1.822739652],"iteration":92,"passed_time":0.08298319224,"remaining_time":0.006246046728},
{"learn":[1.820575218],"iteration":93,"passed_time":0.08334113276,"remaining_time":0.005319646772},
{"learn":[1.818515302],"iteration":94,"passed_time":0.08370332817,"remaining_time":0.004405438325},
{"learn":[1.795924191],"iteration":95,"passed_time":0.08462988148,"remaining_time":0.003526245062},
{"learn":[1.781633822],"iteration":96,"passed_time":0.08557768973,"remaining_time":0.002646732672},
{"learn":[1.762012559],"iteration":97,"passed_time":0.0865629843,"remaining_time":0.001766591516},
{"learn":[1.760022665],"iteration":98,"passed_time":0.08704444839,"remaining_time":0.0008792368524},
{"learn":[1.748935643],"iteration":99,"passed_time":0.08794461614,"remaining_time":0}
]}